databalancer/__init__.py
databalancer/databalancer.py
databalancer/paraphraseGeneratorClient.py
databalancer/paraphraseInputGeneratorClient.py
databalancer-0.0.8.dist-info/LICENSE
databalancer-0.0.8.dist-info/METADATA
databalancer-0.0.8.dist-info/WHEEL
databalancer-0.0.8.dist-info/top_level.txt
databalancer-0.0.8.dist-info/RECORD
