Metadata-Version: 2.1
Name: databalancer
Version: 0.0.8
Summary: Databalancer is the python library dedicated to balance the imbalanced text classification datasets before the model training in machine learning applications
Home-page: https://github.com/pradeepdev-1995/databalancer
Author: Pradeep T
Author-email: pradeeprajkvr@gmail.com
License: Apache License 2.0
Platform: UNKNOWN
Classifier: Development Status :: 5 - Production/Stable
Classifier: License :: OSI Approved :: Apache Software License
Classifier: Programming Language :: Python :: 3.6
Classifier: Topic :: Software Development :: Libraries
Classifier: Topic :: Software Development :: Libraries :: Python Modules
Classifier: Intended Audience :: Developers
Requires-Python: >=3.6.9
Requires-Dist: numpy (==1.17.4)
Requires-Dist: pandas (==1.1.4)
Requires-Dist: pytorch-lightning (==0.7.5)
Requires-Dist: pytorch-transformers (==1.1.0)
Requires-Dist: torch (==1.8.0)
Requires-Dist: torchfile (==0.1.0)
Requires-Dist: transformers (==4.9.1)
Requires-Dist: matplotlib (==3.3.3)
